<?xml version="1.0" encoding="utf-8"?>
<!DOCTYPE xml>
<!-- this file was auto-generated. Do not modify it manually -->
<PinInformation>
  <Dependence Dependence=""/>
  <Pin Id="B1" PinNumber="B1">
    <Function Id="P5_3" FunctionName="P5_3" PinInputOutput="IO"/>
    <Function Id="D3" FunctionName="D3" PinInputOutput="IO"/>
    <Function Id="MMC_D7" FunctionName="MMC_D7" PinInputOutput="IO"/>
    <Function Id="ET_TXD3" FunctionName="ET_TXD3" PinInputOutput="O"/>
    <Function Id="DV0_DATA19" FunctionName="DV0_DATA19" PinInputOutput="I"/>
    <Function Id="LCD0_TCON3" FunctionName="LCD0_TCON3" PinInputOutput="O"/>
  </Pin>
  <Pin Id="C2" PinNumber="C2">
    <Function Id="P5_4" FunctionName="P5_4" PinInputOutput="IO"/>
    <Function Id="D4" FunctionName="D4" PinInputOutput="IO"/>
    <Function Id="RSPCK2" FunctionName="RSPCK2" PinInputOutput="IO"/>
    <Function Id="SSISCK1" FunctionName="SSISCK1" PinInputOutput="IO"/>
    <Function Id="DV0_DATA20" FunctionName="DV0_DATA20" PinInputOutput="I"/>
  </Pin>
  <Pin Id="D2" PinNumber="D2">
    <Function Id="P5_5" FunctionName="P5_5" PinInputOutput="IO"/>
    <Function Id="D5" FunctionName="D5" PinInputOutput="IO"/>
    <Function Id="SSL20" FunctionName="SSL20" PinInputOutput="IO"/>
    <Function Id="SSIWS1" FunctionName="SSIWS1" PinInputOutput="IO"/>
    <Function Id="DV0_DATA21" FunctionName="DV0_DATA21" PinInputOutput="I"/>
  </Pin>
  <Pin Id="C1" PinNumber="C1">
    <Function Id="P5_6" FunctionName="P5_6" PinInputOutput="IO"/>
    <Function Id="D6" FunctionName="D6" PinInputOutput="IO"/>
    <Function Id="MOSI2" FunctionName="MOSI2" PinInputOutput="IO"/>
    <Function Id="SSITxD1" FunctionName="SSITxD1" PinInputOutput="O"/>
    <Function Id="DV0_DATA22" FunctionName="DV0_DATA22" PinInputOutput="I"/>
    <Function Id="SCK2" FunctionName="SCK2" PinInputOutput="IO"/>
  </Pin>
  <Pin Id="D1" PinNumber="D1">
    <Function Id="P5_7" FunctionName="P5_7" PinInputOutput="IO"/>
    <Function Id="D7" FunctionName="D7" PinInputOutput="IO"/>
    <Function Id="MISO2" FunctionName="MISO2" PinInputOutput="IO"/>
    <Function Id="SSIRxD1" FunctionName="SSIRxD1" PinInputOutput="I"/>
    <Function Id="DV0_DATA23" FunctionName="DV0_DATA23" PinInputOutput="I"/>
    <Function Id="TxD2" FunctionName="TxD2" PinInputOutput="O"/>
  </Pin>
  <Pin Id="D3" PinNumber="D3">
    <Function Id="P5_8" FunctionName="P5_8" PinInputOutput="IO"/>
    <Function Id="D8" FunctionName="D8" PinInputOutput="IO"/>
    <Function Id="CAN0RX" FunctionName="CAN0RX" PinInputOutput="I"/>
    <Function Id="TIOC4A" FunctionName="TIOC4A" PinInputOutput="IO"/>
    <Function Id="IRQ3" FunctionName="IRQ3" PinInputOutput="I"/>
  </Pin>
  <Pin Id="A2" PinNumber="A2">
    <Function Id="Vcc" FunctionName="Vcc" PinInputOutput="-"/>
  </Pin>
  <Pin Id="E3" PinNumber="E3">
    <Function Id="P5_9" FunctionName="P5_9" PinInputOutput="IO"/>
    <Function Id="D9" FunctionName="D9" PinInputOutput="IO"/>
    <Function Id="CAN0TX" FunctionName="CAN0TX" PinInputOutput="O"/>
    <Function Id="TIOC4B" FunctionName="TIOC4B" PinInputOutput="IO"/>
    <Function Id="IRQ4" FunctionName="IRQ4" PinInputOutput="I"/>
  </Pin>
  <Pin Id="A1" PinNumber="A1">
    <Function Id="Vss" FunctionName="Vss" PinInputOutput="-"/>
  </Pin>
  <Pin Id="E1" PinNumber="E1">
    <Function Id="P5_10" FunctionName="P5_10" PinInputOutput="IO"/>
    <Function Id="D10" FunctionName="D10" PinInputOutput="IO"/>
    <Function Id="IERxD" FunctionName="IERxD" PinInputOutput="I"/>
    <Function Id="TIOC4C" FunctionName="TIOC4C" PinInputOutput="IO"/>
    <Function Id="IRQ5" FunctionName="IRQ5" PinInputOutput="I"/>
  </Pin>
  <Pin Id="D4" PinNumber="D4">
    <Function Id="PVcc" FunctionName="PVcc" PinInputOutput="-"/>
  </Pin>
  <Pin Id="E2" PinNumber="E2">
    <Function Id="P5_11" FunctionName="P5_11" PinInputOutput="IO"/>
    <Function Id="D11" FunctionName="D11" PinInputOutput="IO"/>
    <Function Id="IETxD" FunctionName="IETxD" PinInputOutput="O"/>
    <Function Id="TIOC4D" FunctionName="TIOC4D" PinInputOutput="IO"/>
    <Function Id="IRQ6" FunctionName="IRQ6" PinInputOutput="I"/>
  </Pin>
  <Pin Id="F2" PinNumber="F2">
    <Function Id="P5_12" FunctionName="P5_12" PinInputOutput="IO"/>
    <Function Id="D12" FunctionName="D12" PinInputOutput="IO"/>
    <Function Id="SSISCK2" FunctionName="SSISCK2" PinInputOutput="IO"/>
    <Function Id="SCK4" FunctionName="SCK4" PinInputOutput="IO"/>
    <Function Id="AUDIO_XOUT2" FunctionName="AUDIO_XOUT2" PinInputOutput="O"/>
  </Pin>
  <Pin Id="F4" PinNumber="F4">
    <Function Id="P5_13" FunctionName="P5_13" PinInputOutput="IO"/>
    <Function Id="D13" FunctionName="D13" PinInputOutput="IO"/>
    <Function Id="SSIWS2" FunctionName="SSIWS2" PinInputOutput="IO"/>
    <Function Id="AUDIO_XOUT" FunctionName="AUDIO_XOUT" PinInputOutput="O"/>
    <Function Id="AUDIO_XOUT3" FunctionName="AUDIO_XOUT3" PinInputOutput="O"/>
  </Pin>
  <Pin Id="F3" PinNumber="F3">
    <Function Id="P5_14" FunctionName="P5_14" PinInputOutput="IO"/>
    <Function Id="D14" FunctionName="D14" PinInputOutput="IO"/>
    <Function Id="SSIDATA2" FunctionName="SSIDATA2" PinInputOutput="IO"/>
    <Function Id="RxD4" FunctionName="RxD4" PinInputOutput="I"/>
    <Function Id="TIOC2A" FunctionName="TIOC2A" PinInputOutput="IO"/>
  </Pin>
  <Pin Id="F1" PinNumber="F1">
    <Function Id="P5_15" FunctionName="P5_15" PinInputOutput="IO"/>
    <Function Id="D15" FunctionName="D15" PinInputOutput="IO"/>
    <Function Id="SD_WP_1" FunctionName="SD_WP_1" PinInputOutput="I"/>
    <Function Id="TxD4" FunctionName="TxD4" PinInputOutput="O"/>
  </Pin>
  <Pin Id="G3" PinNumber="G3">
    <Function Id="P6_0" FunctionName="P6_0" PinInputOutput="IO"/>
    <Function Id="D16" FunctionName="D16" PinInputOutput="IO"/>
    <Function Id="LCD0_DATA8" FunctionName="LCD0_DATA8" PinInputOutput="O"/>
    <Function Id="RSPCK0" FunctionName="RSPCK0" PinInputOutput="IO"/>
    <Function Id="TCLKA" FunctionName="TCLKA" PinInputOutput="I"/>
    <Function Id="WDTOVF#" FunctionName="WDTOVF#" PinInputOutput="O"/>
  </Pin>
  <Pin Id="A7" PinNumber="A7">
    <Function Id="Vss" FunctionName="Vss" PinInputOutput="-"/>
  </Pin>
  <Pin Id="G2" PinNumber="G2">
    <Function Id="P6_1" FunctionName="P6_1" PinInputOutput="IO"/>
    <Function Id="D17" FunctionName="D17" PinInputOutput="IO"/>
    <Function Id="LCD0_DATA9" FunctionName="LCD0_DATA9" PinInputOutput="O"/>
    <Function Id="SSL00" FunctionName="SSL00" PinInputOutput="IO"/>
    <Function Id="TCLKB" FunctionName="TCLKB" PinInputOutput="I"/>
  </Pin>
  <Pin Id="G1" PinNumber="G1">
    <Function Id="P6_2" FunctionName="P6_2" PinInputOutput="IO"/>
    <Function Id="D18" FunctionName="D18" PinInputOutput="IO"/>
    <Function Id="LCD0_DATA10" FunctionName="LCD0_DATA10" PinInputOutput="O"/>
    <Function Id="MOSI0" FunctionName="MOSI0" PinInputOutput="IO"/>
    <Function Id="TCLKC" FunctionName="TCLKC" PinInputOutput="I"/>
  </Pin>
  <Pin Id="B3" PinNumber="B3">
    <Function Id="Vcc" FunctionName="Vcc" PinInputOutput="-"/>
  </Pin>
  <Pin Id="H3" PinNumber="H3">
    <Function Id="P6_3" FunctionName="P6_3" PinInputOutput="IO"/>
    <Function Id="D19" FunctionName="D19" PinInputOutput="IO"/>
    <Function Id="LCD0_DATA11" FunctionName="LCD0_DATA11" PinInputOutput="O"/>
    <Function Id="MISO0" FunctionName="MISO0" PinInputOutput="IO"/>
    <Function Id="TCLKD" FunctionName="TCLKD" PinInputOutput="I"/>
  </Pin>
  <Pin Id="A8" PinNumber="A8">
    <Function Id="Vss" FunctionName="Vss" PinInputOutput="-"/>
  </Pin>
  <Pin Id="H2" PinNumber="H2">
    <Function Id="P6_4" FunctionName="P6_4" PinInputOutput="IO"/>
    <Function Id="D20" FunctionName="D20" PinInputOutput="IO"/>
    <Function Id="LCD0_DATA12" FunctionName="LCD0_DATA12" PinInputOutput="O"/>
    <Function Id="SSISCK3" FunctionName="SSISCK3" PinInputOutput="IO"/>
    <Function Id="MLB_CLK" FunctionName="MLB_CLK" PinInputOutput="I"/>
  </Pin>
  <Pin Id="D11" PinNumber="D11">
    <Function Id="PVcc" FunctionName="PVcc" PinInputOutput="-"/>
  </Pin>
  <Pin Id="H1" PinNumber="H1">
    <Function Id="P6_5" FunctionName="P6_5" PinInputOutput="IO"/>
    <Function Id="D21" FunctionName="D21" PinInputOutput="IO"/>
    <Function Id="LCD0_DATA13" FunctionName="LCD0_DATA13" PinInputOutput="O"/>
    <Function Id="SSIWS3" FunctionName="SSIWS3" PinInputOutput="IO"/>
    <Function Id="MLB_SIG" FunctionName="MLB_SIG" PinInputOutput="IO"/>
  </Pin>
  <Pin Id="J4" PinNumber="J4">
    <Function Id="P6_6" FunctionName="P6_6" PinInputOutput="IO"/>
    <Function Id="D22" FunctionName="D22" PinInputOutput="IO"/>
    <Function Id="LCD0_DATA14" FunctionName="LCD0_DATA14" PinInputOutput="O"/>
    <Function Id="SSITxD3" FunctionName="SSITxD3" PinInputOutput="O"/>
    <Function Id="MLB_DAT" FunctionName="MLB_DAT" PinInputOutput="IO"/>
  </Pin>
  <Pin Id="J1" PinNumber="J1">
    <Function Id="P6_7" FunctionName="P6_7" PinInputOutput="IO"/>
    <Function Id="D23" FunctionName="D23" PinInputOutput="IO"/>
    <Function Id="LCD0_DATA15" FunctionName="LCD0_DATA15" PinInputOutput="O"/>
    <Function Id="SSIRxD3" FunctionName="SSIRxD3" PinInputOutput="I"/>
    <Function Id="IRQ0" FunctionName="IRQ0" PinInputOutput="I"/>
    <Function Id="TIOC3A" FunctionName="TIOC3A" PinInputOutput="IO"/>
    <Function Id="RLIN30RX" FunctionName="RLIN30RX" PinInputOutput="I"/>
  </Pin>
  <Pin Id="J3" PinNumber="J3">
    <Function Id="P6_8" FunctionName="P6_8" PinInputOutput="IO"/>
    <Function Id="D24" FunctionName="D24" PinInputOutput="IO"/>
    <Function Id="LCD0_DATA16" FunctionName="LCD0_DATA16" PinInputOutput="O"/>
    <Function Id="SSISCK0" FunctionName="SSISCK0" PinInputOutput="IO"/>
    <Function Id="IRQ1" FunctionName="IRQ1" PinInputOutput="I"/>
    <Function Id="TIOC3B" FunctionName="TIOC3B" PinInputOutput="IO"/>
    <Function Id="RLIN30TX" FunctionName="RLIN30TX" PinInputOutput="O"/>
  </Pin>
  <Pin Id="A11" PinNumber="A11">
    <Function Id="Vss" FunctionName="Vss" PinInputOutput="-"/>
  </Pin>
  <Pin Id="D13" PinNumber="D13">
    <Function Id="PVcc" FunctionName="PVcc" PinInputOutput="-"/>
  </Pin>
  <Pin Id="J2" PinNumber="J2">
    <Function Id="P6_9" FunctionName="P6_9" PinInputOutput="IO"/>
    <Function Id="D25" FunctionName="D25" PinInputOutput="IO"/>
    <Function Id="LCD0_DATA17" FunctionName="LCD0_DATA17" PinInputOutput="O"/>
    <Function Id="SSIWS0" FunctionName="SSIWS0" PinInputOutput="IO"/>
    <Function Id="IRQ2" FunctionName="IRQ2" PinInputOutput="I"/>
    <Function Id="TIOC3C" FunctionName="TIOC3C" PinInputOutput="IO"/>
  </Pin>
  <Pin Id="A15" PinNumber="A15">
    <Function Id="Vss" FunctionName="Vss" PinInputOutput="-"/>
  </Pin>
  <Pin Id="K1" PinNumber="K1">
    <Function Id="P6_10" FunctionName="P6_10" PinInputOutput="IO"/>
    <Function Id="D26" FunctionName="D26" PinInputOutput="IO"/>
    <Function Id="LCD0_DATA18" FunctionName="LCD0_DATA18" PinInputOutput="O"/>
    <Function Id="SSITxD0" FunctionName="SSITxD0" PinInputOutput="O"/>
    <Function Id="IRQ3" FunctionName="IRQ3" PinInputOutput="I"/>
    <Function Id="TIOC3D" FunctionName="TIOC3D" PinInputOutput="IO"/>
    <Function Id="CAN1TX" FunctionName="CAN1TX" PinInputOutput="O"/>
  </Pin>
  <Pin Id="K2" PinNumber="K2">
    <Function Id="P6_11" FunctionName="P6_11" PinInputOutput="IO"/>
    <Function Id="D27" FunctionName="D27" PinInputOutput="IO"/>
    <Function Id="LCD0_DATA19" FunctionName="LCD0_DATA19" PinInputOutput="O"/>
    <Function Id="SSIRxD0" FunctionName="SSIRxD0" PinInputOutput="I"/>
    <Function Id="SSIDATA2" FunctionName="SSIDATA2" PinInputOutput="IO"/>
    <Function Id="SCK0" FunctionName="SCK0" PinInputOutput="IO"/>
    <Function Id="CAN1RX" FunctionName="CAN1RX" PinInputOutput="I"/>
  </Pin>
  <Pin Id="C4" PinNumber="C4">
    <Function Id="Vcc" FunctionName="Vcc" PinInputOutput="-"/>
  </Pin>
  <Pin Id="K3" PinNumber="K3">
    <Function Id="P6_12" FunctionName="P6_12" PinInputOutput="IO"/>
    <Function Id="D28" FunctionName="D28" PinInputOutput="IO"/>
    <Function Id="LCD0_DATA20" FunctionName="LCD0_DATA20" PinInputOutput="O"/>
    <Function Id="RSPCK1" FunctionName="RSPCK1" PinInputOutput="IO"/>
    <Function Id="SSISCK2" FunctionName="SSISCK2" PinInputOutput="IO"/>
    <Function Id="RTS0#" FunctionName="RTS0#" PinInputOutput="IO"/>
    <Function Id="DV0_DATA0" FunctionName="DV0_DATA0" PinInputOutput="I"/>
  </Pin>
  <Pin Id="B2" PinNumber="B2">
    <Function Id="Vss" FunctionName="Vss" PinInputOutput="-"/>
  </Pin>
  <Pin Id="M1" PinNumber="M1">
    <Function Id="CKIO" FunctionName="CKIO" PinInputOutput="O"/>
  </Pin>
  <Pin Id="L2" PinNumber="L2">
    <Function Id="P6_13" FunctionName="P6_13" PinInputOutput="IO"/>
    <Function Id="D29" FunctionName="D29" PinInputOutput="IO"/>
    <Function Id="LCD0_DATA21" FunctionName="LCD0_DATA21" PinInputOutput="O"/>
    <Function Id="SSL10" FunctionName="SSL10" PinInputOutput="IO"/>
    <Function Id="SSIWS2" FunctionName="SSIWS2" PinInputOutput="IO"/>
    <Function Id="CTS0#" FunctionName="CTS0#" PinInputOutput="IO"/>
    <Function Id="DV0_DATA1" FunctionName="DV0_DATA1" PinInputOutput="I"/>
  </Pin>
  <Pin Id="E4" PinNumber="E4">
    <Function Id="PVcc" FunctionName="PVcc" PinInputOutput="-"/>
  </Pin>
  <Pin Id="M2" PinNumber="M2">
    <Function Id="P6_14" FunctionName="P6_14" PinInputOutput="IO"/>
    <Function Id="D30" FunctionName="D30" PinInputOutput="IO"/>
    <Function Id="LCD0_DATA22" FunctionName="LCD0_DATA22" PinInputOutput="O"/>
    <Function Id="MOSI1" FunctionName="MOSI1" PinInputOutput="IO"/>
    <Function Id="SSIDATA2" FunctionName="SSIDATA2" PinInputOutput="IO"/>
    <Function Id="RxD0" FunctionName="RxD0" PinInputOutput="I"/>
    <Function Id="DV0_DATA2" FunctionName="DV0_DATA2" PinInputOutput="I"/>
  </Pin>
  <Pin Id="L3" PinNumber="L3">
    <Function Id="P6_15" FunctionName="P6_15" PinInputOutput="IO"/>
    <Function Id="D31" FunctionName="D31" PinInputOutput="IO"/>
    <Function Id="LCD0_DATA23" FunctionName="LCD0_DATA23" PinInputOutput="O"/>
    <Function Id="MISO1" FunctionName="MISO1" PinInputOutput="IO"/>
    <Function Id="TxD0" FunctionName="TxD0" PinInputOutput="O"/>
    <Function Id="DV0_DATA3" FunctionName="DV0_DATA3" PinInputOutput="I"/>
  </Pin>
  <Pin Id="N2" PinNumber="N2">
    <Function Id="P7_0" FunctionName="P7_0" PinInputOutput="IO"/>
    <Function Id="LCD0_EXTCLK" FunctionName="LCD0_EXTCLK" PinInputOutput="I"/>
    <Function Id="MMC_CD" FunctionName="MMC_CD" PinInputOutput="I"/>
    <Function Id="SD_CD_1" FunctionName="SD_CD_1" PinInputOutput="I"/>
    <Function Id="SPDIF_OUT" FunctionName="SPDIF_OUT" PinInputOutput="O"/>
    <Function Id="TIOC2A" FunctionName="TIOC2A" PinInputOutput="IO"/>
    <Function Id="DV0_DATA4" FunctionName="DV0_DATA4" PinInputOutput="I"/>
    <Function Id="SCI_SCK0" FunctionName="SCI_SCK0" PinInputOutput="IO"/>
  </Pin>
  <Pin Id="M3" PinNumber="M3">
    <Function Id="P7_1" FunctionName="P7_1" PinInputOutput="IO"/>
    <Function Id="CS1#" FunctionName="CS1#" PinInputOutput="O"/>
    <Function Id="AUDIO_XOUT" FunctionName="AUDIO_XOUT" PinInputOutput="O"/>
    <Function Id="SD_WP_1" FunctionName="SD_WP_1" PinInputOutput="I"/>
    <Function Id="TxD2" FunctionName="TxD2" PinInputOutput="O"/>
    <Function Id="DV0_DATA5" FunctionName="DV0_DATA5" PinInputOutput="I"/>
    <Function Id="SCI_RXD0/IrRXD" FunctionName="SCI_RXD0/IrRXD" PinInputOutput="I"/>
  </Pin>
  <Pin Id="N1" PinNumber="N1">
    <Function Id="P7_2" FunctionName="P7_2" PinInputOutput="IO"/>
    <Function Id="CS4#" FunctionName="CS4#" PinInputOutput="O"/>
    <Function Id="MMC_D1" FunctionName="MMC_D1" PinInputOutput="IO"/>
    <Function Id="SD_D1_1" FunctionName="SD_D1_1" PinInputOutput="IO"/>
    <Function Id="IRQ4" FunctionName="IRQ4" PinInputOutput="I"/>
    <Function Id="CAN0RX" FunctionName="CAN0RX" PinInputOutput="I"/>
    <Function Id="DV0_DATA6" FunctionName="DV0_DATA6" PinInputOutput="I"/>
    <Function Id="SCI_TXD0/IrTXD" FunctionName="SCI_TXD0/IrTXD" PinInputOutput="O"/>
  </Pin>
  <Pin Id="P3" PinNumber="P3">
    <Function Id="P7_3" FunctionName="P7_3" PinInputOutput="IO"/>
    <Function Id="CS5#" FunctionName="CS5#" PinInputOutput="O"/>
    <Function Id="MMC_D0" FunctionName="MMC_D0" PinInputOutput="IO"/>
    <Function Id="SD_D0_1" FunctionName="SD_D0_1" PinInputOutput="IO"/>
    <Function Id="IRQ3" FunctionName="IRQ3" PinInputOutput="I"/>
    <Function Id="CAN0TX" FunctionName="CAN0TX" PinInputOutput="O"/>
    <Function Id="DV0_DATA7" FunctionName="DV0_DATA7" PinInputOutput="I"/>
    <Function Id="SCI_CTS0#/RTS0#" FunctionName="SCI_CTS0#/RTS0#" PinInputOutput="IO"/>
  </Pin>
  <Pin Id="L1" PinNumber="L1">
    <Function Id="Vss" FunctionName="Vss" PinInputOutput="-"/>
  </Pin>
  <Pin Id="R2" PinNumber="R2">
    <Function Id="P7_4" FunctionName="P7_4" PinInputOutput="IO"/>
    <Function Id="WAIT#" FunctionName="WAIT#" PinInputOutput="I"/>
    <Function Id="MMC_CLK" FunctionName="MMC_CLK" PinInputOutput="O"/>
    <Function Id="SD_CLK_1" FunctionName="SD_CLK_1" PinInputOutput="O"/>
    <Function Id="IETxD" FunctionName="IETxD" PinInputOutput="O"/>
    <Function Id="LCD0_CLK" FunctionName="LCD0_CLK" PinInputOutput="O"/>
    <Function Id="SCI_SCK1" FunctionName="SCI_SCK1" PinInputOutput="IO"/>
  </Pin>
  <Pin Id="N4" PinNumber="N4">
    <Function Id="P7_5" FunctionName="P7_5" PinInputOutput="IO"/>
    <Function Id="BS#" FunctionName="BS#" PinInputOutput="O"/>
    <Function Id="MMC_CMD" FunctionName="MMC_CMD" PinInputOutput="IO"/>
    <Function Id="SD_CMD_1" FunctionName="SD_CMD_1" PinInputOutput="IO"/>
    <Function Id="TxD0" FunctionName="TxD0" PinInputOutput="O"/>
    <Function Id="IERxD" FunctionName="IERxD" PinInputOutput="I"/>
    <Function Id="LCD0_TCON4" FunctionName="LCD0_TCON4" PinInputOutput="O"/>
    <Function Id="SCI_RXD1" FunctionName="SCI_RXD1" PinInputOutput="I"/>
  </Pin>
  <Pin Id="P4" PinNumber="P4">
    <Function Id="P7_6" FunctionName="P7_6" PinInputOutput="IO"/>
    <Function Id="WE2#/DQMUL" FunctionName="WE2#/DQMUL" PinInputOutput="O"/>
    <Function Id="MMC_D3" FunctionName="MMC_D3" PinInputOutput="IO"/>
    <Function Id="SD_D3_1" FunctionName="SD_D3_1" PinInputOutput="IO"/>
    <Function Id="IRQ6" FunctionName="IRQ6" PinInputOutput="I"/>
    <Function Id="CTS2#" FunctionName="CTS2#" PinInputOutput="IO"/>
    <Function Id="LCD0_TCON5" FunctionName="LCD0_TCON5" PinInputOutput="O"/>
    <Function Id="SCI_TXD1" FunctionName="SCI_TXD1" PinInputOutput="O"/>
  </Pin>
  <Pin Id="E12" PinNumber="E12">
    <Function Id="PVcc" FunctionName="PVcc" PinInputOutput="-"/>
  </Pin>
  <Pin Id="R4" PinNumber="R4">
    <Function Id="P7_7" FunctionName="P7_7" PinInputOutput="IO"/>
    <Function Id="WE3#/DQMUU/AH#" FunctionName="WE3#/DQMUU/AH#" PinInputOutput="O"/>
    <Function Id="MMC_D2" FunctionName="MMC_D2" PinInputOutput="IO"/>
    <Function Id="SD_D2_1" FunctionName="SD_D2_1" PinInputOutput="IO"/>
    <Function Id="IRQ5" FunctionName="IRQ5" PinInputOutput="I"/>
    <Function Id="RTS2#" FunctionName="RTS2#" PinInputOutput="IO"/>
    <Function Id="LCD0_TCON6" FunctionName="LCD0_TCON6" PinInputOutput="O"/>
    <Function Id="SCI_CTS1#/RTS1#" FunctionName="SCI_CTS1#/RTS1#" PinInputOutput="IO"/>
  </Pin>
  <Pin Id="N5" PinNumber="N5">
    <Function Id="P7_8" FunctionName="P7_8" PinInputOutput="IO"/>
    <Function Id="CS2#" FunctionName="CS2#" PinInputOutput="O"/>
    <Function Id="SSISCK1" FunctionName="SSISCK1" PinInputOutput="IO"/>
    <Function Id="DV0_CLK" FunctionName="DV0_CLK" PinInputOutput="I"/>
    <Function Id="IRQ3" FunctionName="IRQ3" PinInputOutput="I"/>
    <Function Id="TxD0" FunctionName="TxD0" PinInputOutput="O"/>
  </Pin>
  <Pin Id="R5" PinNumber="R5">
    <Function Id="P7_9" FunctionName="P7_9" PinInputOutput="IO"/>
    <Function Id="A25" FunctionName="A25" PinInputOutput="O"/>
    <Function Id="SSIWS1" FunctionName="SSIWS1" PinInputOutput="IO"/>
    <Function Id="DV0_VSYNC" FunctionName="DV0_VSYNC" PinInputOutput="I"/>
    <Function Id="IRQ5" FunctionName="IRQ5" PinInputOutput="I"/>
    <Function Id="SCK3" FunctionName="SCK3" PinInputOutput="IO"/>
    <Function Id="TIOC1A" FunctionName="TIOC1A" PinInputOutput="IO"/>
  </Pin>
  <Pin Id="P5" PinNumber="P5">
    <Function Id="P7_10" FunctionName="P7_10" PinInputOutput="IO"/>
    <Function Id="TEND0" FunctionName="TEND0" PinInputOutput="O"/>
    <Function Id="SSITxD1" FunctionName="SSITxD1" PinInputOutput="O"/>
    <Function Id="DV0_HSYNC" FunctionName="DV0_HSYNC" PinInputOutput="I"/>
    <Function Id="RxD3" FunctionName="RxD3" PinInputOutput="I"/>
  </Pin>
  <Pin Id="N6" PinNumber="N6">
    <Function Id="P7_11" FunctionName="P7_11" PinInputOutput="IO"/>
    <Function Id="DACK0" FunctionName="DACK0" PinInputOutput="O"/>
    <Function Id="SSIRxD1" FunctionName="SSIRxD1" PinInputOutput="I"/>
    <Function Id="CAN_CLK" FunctionName="CAN_CLK" PinInputOutput="I"/>
    <Function Id="SCK2" FunctionName="SCK2" PinInputOutput="IO"/>
    <Function Id="TxD3" FunctionName="TxD3" PinInputOutput="O"/>
    <Function Id="AUDIO_XOUT" FunctionName="AUDIO_XOUT" PinInputOutput="O"/>
    <Function Id="AUDIO_XOUT3" FunctionName="AUDIO_XOUT3" PinInputOutput="O"/>
  </Pin>
  <Pin Id="C3" PinNumber="C3">
    <Function Id="Vss" FunctionName="Vss" PinInputOutput="-"/>
  </Pin>
  <Pin Id="F12" PinNumber="F12">
    <Function Id="PVcc" FunctionName="PVcc" PinInputOutput="-"/>
  </Pin>
  <Pin Id="P6" PinNumber="P6">
    <Function Id="P2_0" FunctionName="P2_0" PinInputOutput="IO"/>
    <Function Id="CS3#" FunctionName="CS3#" PinInputOutput="O"/>
    <Function Id="RLIN30RX" FunctionName="RLIN30RX" PinInputOutput="I"/>
    <Function Id="SPDIF_IN" FunctionName="SPDIF_IN" PinInputOutput="I"/>
    <Function Id="IRQ7" FunctionName="IRQ7" PinInputOutput="I"/>
  </Pin>
  <Pin Id="R6" PinNumber="R6">
    <Function Id="P2_1" FunctionName="P2_1" PinInputOutput="IO"/>
    <Function Id="RAS#" FunctionName="RAS#" PinInputOutput="O"/>
    <Function Id="RLIN30TX" FunctionName="RLIN30TX" PinInputOutput="O"/>
    <Function Id="SPDIF_OUT" FunctionName="SPDIF_OUT" PinInputOutput="O"/>
    <Function Id="IRQ6" FunctionName="IRQ6" PinInputOutput="I"/>
  </Pin>
  <Pin Id="D5" PinNumber="D5">
    <Function Id="Vcc" FunctionName="Vcc" PinInputOutput="-"/>
  </Pin>
  <Pin Id="P7" PinNumber="P7">
    <Function Id="P2_2" FunctionName="P2_2" PinInputOutput="IO"/>
    <Function Id="CAS#" FunctionName="CAS#" PinInputOutput="O"/>
    <Function Id="CAN1RX" FunctionName="CAN1RX" PinInputOutput="I"/>
    <Function Id="TIOC0C" FunctionName="TIOC0C" PinInputOutput="IO"/>
    <Function Id="IRQ5" FunctionName="IRQ5" PinInputOutput="I"/>
  </Pin>
  <Pin Id="R7" PinNumber="R7">
    <Function Id="P2_3" FunctionName="P2_3" PinInputOutput="IO"/>
    <Function Id="CKE" FunctionName="CKE" PinInputOutput="O"/>
    <Function Id="CAN1TX" FunctionName="CAN1TX" PinInputOutput="O"/>
    <Function Id="TIOC0D" FunctionName="TIOC0D" PinInputOutput="IO"/>
  </Pin>
  <Pin Id="C11" PinNumber="C11">
    <Function Id="Vss" FunctionName="Vss" PinInputOutput="-"/>
  </Pin>
  <Pin Id="K4" PinNumber="K4">
    <Function Id="PVcc" FunctionName="PVcc" PinInputOutput="-"/>
  </Pin>
  <Pin Id="M7" PinNumber="M7">
    <Function Id="P0_0" FunctionName="P0_0" PinInputOutput="I"/>
    <Function Id="MD_BOOT0" FunctionName="MD_BOOT0" PinInputOutput="I"/>
    <Function Id="RxD0" FunctionName="RxD0" PinInputOutput="I"/>
    <Function Id="IRQ4" FunctionName="IRQ4" PinInputOutput="I"/>
  </Pin>
  <Pin Id="N7" PinNumber="N7">
    <Function Id="P0_1" FunctionName="P0_1" PinInputOutput="I"/>
    <Function Id="MD_BOOT1" FunctionName="MD_BOOT1" PinInputOutput="I"/>
    <Function Id="RxD2" FunctionName="RxD2" PinInputOutput="I"/>
    <Function Id="SSIRxD3" FunctionName="SSIRxD3" PinInputOutput="I"/>
    <Function Id="ADTRG#" FunctionName="ADTRG#" PinInputOutput="I"/>
  </Pin>
  <Pin Id="M8" PinNumber="M8">
    <Function Id="P0_2" FunctionName="P0_2" PinInputOutput="I"/>
    <Function Id="MD_CLK" FunctionName="MD_CLK" PinInputOutput="I"/>
    <Function Id="RxD1" FunctionName="RxD1" PinInputOutput="I"/>
    <Function Id="IRQ7" FunctionName="IRQ7" PinInputOutput="I"/>
  </Pin>
  <Pin Id="M6" PinNumber="M6">
    <Function Id="P0_3" FunctionName="P0_3" PinInputOutput="I"/>
    <Function Id="MD_CLKS" FunctionName="MD_CLKS" PinInputOutput="I"/>
    <Function Id="RxD3" FunctionName="RxD3" PinInputOutput="I"/>
    <Function Id="SPDIF_IN" FunctionName="SPDIF_IN" PinInputOutput="I"/>
  </Pin>
  <Pin Id="P8" PinNumber="P8">
    <Function Id="RTC_X1" FunctionName="RTC_X1" PinInputOutput="I"/>
  </Pin>
  <Pin Id="R8" PinNumber="R8">
    <Function Id="RTC_X2" FunctionName="RTC_X2" PinInputOutput="O"/>
  </Pin>
  <Pin Id="M9" PinNumber="M9">
    <Function Id="PLLVcc" FunctionName="PLLVcc" PinInputOutput="-"/>
  </Pin>
  <Pin Id="R9" PinNumber="R9">
    <Function Id="EXTAL" FunctionName="EXTAL" PinInputOutput="I"/>
  </Pin>
  <Pin Id="P9" PinNumber="P9">
    <Function Id="XTAL" FunctionName="XTAL" PinInputOutput="O"/>
  </Pin>
  <Pin Id="D8" PinNumber="D8">
    <Function Id="Vss" FunctionName="Vss" PinInputOutput="-"/>
  </Pin>
  <Pin Id="D9" PinNumber="D9">
    <Function Id="Vss" FunctionName="Vss" PinInputOutput="-"/>
  </Pin>
  <Pin Id="N9" PinNumber="N9">
    <Function Id="NMI" FunctionName="NMI" PinInputOutput="I"/>
  </Pin>
  <Pin Id="G4" PinNumber="G4">
    <Function Id="Vss" FunctionName="Vss" PinInputOutput="-"/>
  </Pin>
  <Pin Id="R10" PinNumber="R10">
    <Function Id="RES#" FunctionName="RES#" PinInputOutput="I"/>
  </Pin>
  <Pin Id="L4" PinNumber="L4">
    <Function Id="PVcc" FunctionName="PVcc" PinInputOutput="-"/>
  </Pin>
  <Pin Id="P10" PinNumber="P10">
    <Function Id="P1_8" FunctionName="P1_8" PinInputOutput="I"/>
    <Function Id="AN0" FunctionName="AN0" PinInputOutput="I"/>
    <Function Id="IRQ0" FunctionName="IRQ0" PinInputOutput="I"/>
    <Function Id="RxD0" FunctionName="RxD0" PinInputOutput="I"/>
    <Function Id="DV0_DATA4" FunctionName="DV0_DATA4" PinInputOutput="I"/>
  </Pin>
  <Pin Id="N10" PinNumber="N10">
    <Function Id="P1_9" FunctionName="P1_9" PinInputOutput="I"/>
    <Function Id="AN1" FunctionName="AN1" PinInputOutput="I"/>
    <Function Id="IRQ1" FunctionName="IRQ1" PinInputOutput="I"/>
    <Function Id="RxD1" FunctionName="RxD1" PinInputOutput="I"/>
    <Function Id="DV0_DATA5" FunctionName="DV0_DATA5" PinInputOutput="I"/>
  </Pin>
  <Pin Id="R11" PinNumber="R11">
    <Function Id="P1_10" FunctionName="P1_10" PinInputOutput="I"/>
    <Function Id="AN2" FunctionName="AN2" PinInputOutput="I"/>
    <Function Id="IRQ2" FunctionName="IRQ2" PinInputOutput="I"/>
    <Function Id="RxD2" FunctionName="RxD2" PinInputOutput="I"/>
    <Function Id="DV0_DATA6" FunctionName="DV0_DATA6" PinInputOutput="I"/>
  </Pin>
  <Pin Id="N11" PinNumber="N11">
    <Function Id="P1_11" FunctionName="P1_11" PinInputOutput="I"/>
    <Function Id="AN3" FunctionName="AN3" PinInputOutput="I"/>
    <Function Id="IRQ3" FunctionName="IRQ3" PinInputOutput="I"/>
    <Function Id="RxD3" FunctionName="RxD3" PinInputOutput="I"/>
    <Function Id="DV0_DATA7" FunctionName="DV0_DATA7" PinInputOutput="I"/>
  </Pin>
  <Pin Id="P12" PinNumber="P12">
    <Function Id="P1_12" FunctionName="P1_12" PinInputOutput="I"/>
    <Function Id="AN4" FunctionName="AN4" PinInputOutput="I"/>
    <Function Id="IRQ4" FunctionName="IRQ4" PinInputOutput="I"/>
    <Function Id="ET_RXD0" FunctionName="ET_RXD0" PinInputOutput="I"/>
    <Function Id="VIO_D4" FunctionName="VIO_D4" PinInputOutput="I"/>
  </Pin>
  <Pin Id="P11" PinNumber="P11">
    <Function Id="P1_13" FunctionName="P1_13" PinInputOutput="I"/>
    <Function Id="AN5" FunctionName="AN5" PinInputOutput="I"/>
    <Function Id="IRQ5" FunctionName="IRQ5" PinInputOutput="I"/>
    <Function Id="ET_RXD1" FunctionName="ET_RXD1" PinInputOutput="I"/>
    <Function Id="VIO_D5" FunctionName="VIO_D5" PinInputOutput="I"/>
  </Pin>
  <Pin Id="N12" PinNumber="N12">
    <Function Id="P1_14" FunctionName="P1_14" PinInputOutput="I"/>
    <Function Id="AN6" FunctionName="AN6" PinInputOutput="I"/>
    <Function Id="IRQ6" FunctionName="IRQ6" PinInputOutput="I"/>
    <Function Id="ET_RXD2" FunctionName="ET_RXD2" PinInputOutput="I"/>
    <Function Id="VIO_D6" FunctionName="VIO_D6" PinInputOutput="I"/>
  </Pin>
  <Pin Id="R12" PinNumber="R12">
    <Function Id="P1_15" FunctionName="P1_15" PinInputOutput="I"/>
    <Function Id="AN7" FunctionName="AN7" PinInputOutput="I"/>
    <Function Id="IRQ7" FunctionName="IRQ7" PinInputOutput="I"/>
    <Function Id="ET_RXD3" FunctionName="ET_RXD3" PinInputOutput="I"/>
    <Function Id="VIO_D7" FunctionName="VIO_D7" PinInputOutput="I"/>
  </Pin>
  <Pin Id="P13" PinNumber="P13">
    <Function Id="AVcc" FunctionName="AVcc" PinInputOutput="-"/>
  </Pin>
  <Pin Id="R13" PinNumber="R13">
    <Function Id="AVss" FunctionName="AVss" PinInputOutput="-"/>
  </Pin>
  <Pin Id="R14" PinNumber="R14">
    <Function Id="AVref" FunctionName="AVref" PinInputOutput="-"/>
  </Pin>
  <Pin Id="N14" PinNumber="N14">
    <Function Id="BSCANP" FunctionName="BSCANP" PinInputOutput="I"/>
  </Pin>
  <Pin Id="M5" PinNumber="M5">
    <Function Id="PVcc" FunctionName="PVcc" PinInputOutput="-"/>
  </Pin>
  <Pin Id="P15" PinNumber="P15">
    <Function Id="AUDIO_X1" FunctionName="AUDIO_X1" PinInputOutput="I"/>
  </Pin>
  <Pin Id="N15" PinNumber="N15">
    <Function Id="AUDIO_X2" FunctionName="AUDIO_X2" PinInputOutput="O"/>
  </Pin>
  <Pin Id="H4" PinNumber="H4">
    <Function Id="Vss" FunctionName="Vss" PinInputOutput="-"/>
  </Pin>
  <Pin Id="M14" PinNumber="M14">
    <Function Id="P2_4" FunctionName="P2_4" PinInputOutput="IO"/>
    <Function Id="WE0#/DQMLL" FunctionName="WE0#/DQMLL" PinInputOutput="O"/>
    <Function Id="TIOC4A" FunctionName="TIOC4A" PinInputOutput="IO"/>
  </Pin>
  <Pin Id="D6" PinNumber="D6">
    <Function Id="Vcc" FunctionName="Vcc" PinInputOutput="-"/>
  </Pin>
  <Pin Id="M13" PinNumber="M13">
    <Function Id="P2_5" FunctionName="P2_5" PinInputOutput="IO"/>
    <Function Id="WE1#/WE#/DQMLU" FunctionName="WE1#/WE#/DQMLU" PinInputOutput="O"/>
    <Function Id="TIOC3A" FunctionName="TIOC3A" PinInputOutput="IO"/>
  </Pin>
  <Pin Id="L13" PinNumber="L13">
    <Function Id="TRST#" FunctionName="TRST#" PinInputOutput="I"/>
  </Pin>
  <Pin Id="L14" PinNumber="L14">
    <Function Id="JP0_1" FunctionName="JP0_1" PinInputOutput="I"/>
    <Function Id="TDO" FunctionName="TDO" PinInputOutput="O"/>
  </Pin>
  <Pin Id="L15" PinNumber="L15">
    <Function Id="JP0_0" FunctionName="JP0_0" PinInputOutput="I"/>
    <Function Id="TDI" FunctionName="TDI" PinInputOutput="I"/>
  </Pin>
  <Pin Id="L12" PinNumber="L12">
    <Function Id="TMS" FunctionName="TMS" PinInputOutput="I"/>
  </Pin>
  <Pin Id="K14" PinNumber="K14">
    <Function Id="TCK" FunctionName="TCK" PinInputOutput="I"/>
  </Pin>
  <Pin Id="J12" PinNumber="J12">
    <Function Id="Vss" FunctionName="Vss" PinInputOutput="-"/>
  </Pin>
  <Pin Id="K13" PinNumber="K13">
    <Function Id="P3_0" FunctionName="P3_0" PinInputOutput="IO"/>
    <Function Id="A1" FunctionName="A1" PinInputOutput="O"/>
    <Function Id="SD_D2_0" FunctionName="SD_D2_0" PinInputOutput="IO"/>
    <Function Id="LCD0_DATA0" FunctionName="LCD0_DATA0" PinInputOutput="O"/>
    <Function Id="ET_TXCLK" FunctionName="ET_TXCLK" PinInputOutput="I"/>
  </Pin>
  <Pin Id="K12" PinNumber="K12">
    <Function Id="P3_1" FunctionName="P3_1" PinInputOutput="IO"/>
    <Function Id="A2" FunctionName="A2" PinInputOutput="O"/>
    <Function Id="SD_D3_0" FunctionName="SD_D3_0" PinInputOutput="IO"/>
    <Function Id="LCD0_DATA1" FunctionName="LCD0_DATA1" PinInputOutput="O"/>
    <Function Id="ET_TXER" FunctionName="ET_TXER" PinInputOutput="O"/>
  </Pin>
  <Pin Id="D7" PinNumber="D7">
    <Function Id="Vcc" FunctionName="Vcc" PinInputOutput="-"/>
  </Pin>
  <Pin Id="J13" PinNumber="J13">
    <Function Id="P3_2" FunctionName="P3_2" PinInputOutput="IO"/>
    <Function Id="A3" FunctionName="A3" PinInputOutput="O"/>
    <Function Id="SD_CMD_0" FunctionName="SD_CMD_0" PinInputOutput="IO"/>
    <Function Id="LCD0_DATA2" FunctionName="LCD0_DATA2" PinInputOutput="O"/>
    <Function Id="ET_TXEN" FunctionName="ET_TXEN" PinInputOutput="O"/>
  </Pin>
  <Pin Id="K15" PinNumber="K15">
    <Function Id="Vss" FunctionName="Vss" PinInputOutput="-"/>
  </Pin>
  <Pin Id="J15" PinNumber="J15">
    <Function Id="P3_3" FunctionName="P3_3" PinInputOutput="IO"/>
    <Function Id="A4" FunctionName="A4" PinInputOutput="O"/>
    <Function Id="SD_CLK_0" FunctionName="SD_CLK_0" PinInputOutput="O"/>
    <Function Id="LCD0_DATA3" FunctionName="LCD0_DATA3" PinInputOutput="O"/>
    <Function Id="ET_RXCLK" FunctionName="ET_RXCLK" PinInputOutput="I"/>
  </Pin>
  <Pin Id="M10" PinNumber="M10">
    <Function Id="PVcc" FunctionName="PVcc" PinInputOutput="-"/>
  </Pin>
  <Pin Id="J14" PinNumber="J14">
    <Function Id="P3_4" FunctionName="P3_4" PinInputOutput="IO"/>
    <Function Id="A5" FunctionName="A5" PinInputOutput="O"/>
    <Function Id="SD_D0_0" FunctionName="SD_D0_0" PinInputOutput="IO"/>
    <Function Id="LCD0_DATA4" FunctionName="LCD0_DATA4" PinInputOutput="O"/>
    <Function Id="ET_RXER" FunctionName="ET_RXER" PinInputOutput="I"/>
  </Pin>
  <Pin Id="C13" PinNumber="C13">
    <Function Id="Vss" FunctionName="Vss" PinInputOutput="-"/>
  </Pin>
  <Pin Id="H15" PinNumber="H15">
    <Function Id="P3_5" FunctionName="P3_5" PinInputOutput="IO"/>
    <Function Id="A6" FunctionName="A6" PinInputOutput="O"/>
    <Function Id="SD_D1_0" FunctionName="SD_D1_0" PinInputOutput="IO"/>
    <Function Id="LCD0_DATA5" FunctionName="LCD0_DATA5" PinInputOutput="O"/>
    <Function Id="ET_RXDV" FunctionName="ET_RXDV" PinInputOutput="I"/>
  </Pin>
  <Pin Id="H13" PinNumber="H13">
    <Function Id="P3_6" FunctionName="P3_6" PinInputOutput="IO"/>
    <Function Id="A7" FunctionName="A7" PinInputOutput="O"/>
    <Function Id="SD_WP_0" FunctionName="SD_WP_0" PinInputOutput="I"/>
    <Function Id="LCD0_DATA6" FunctionName="LCD0_DATA6" PinInputOutput="O"/>
    <Function Id="ET_COL" FunctionName="ET_COL" PinInputOutput="I"/>
  </Pin>
  <Pin Id="H14" PinNumber="H14">
    <Function Id="P3_7" FunctionName="P3_7" PinInputOutput="IO"/>
    <Function Id="A8" FunctionName="A8" PinInputOutput="O"/>
    <Function Id="SD_CD_0" FunctionName="SD_CD_0" PinInputOutput="I"/>
    <Function Id="LCD0_DATA7" FunctionName="LCD0_DATA7" PinInputOutput="O"/>
    <Function Id="ET_CRS" FunctionName="ET_CRS" PinInputOutput="I"/>
  </Pin>
  <Pin Id="B14" PinNumber="B14">
    <Function Id="Vss" FunctionName="Vss" PinInputOutput="-"/>
  </Pin>
  <Pin Id="G12" PinNumber="G12">
    <Function Id="P3_8" FunctionName="P3_8" PinInputOutput="IO"/>
    <Function Id="A9" FunctionName="A9" PinInputOutput="O"/>
    <Function Id="AUDIO_CLK" FunctionName="AUDIO_CLK" PinInputOutput="I"/>
    <Function Id="DV0_DATA8" FunctionName="DV0_DATA8" PinInputOutput="I"/>
    <Function Id="SCK3" FunctionName="SCK3" PinInputOutput="IO"/>
  </Pin>
  <Pin Id="G13" PinNumber="G13">
    <Function Id="P3_9" FunctionName="P3_9" PinInputOutput="IO"/>
    <Function Id="A10" FunctionName="A10" PinInputOutput="O"/>
    <Function Id="SPDIF_OUT" FunctionName="SPDIF_OUT" PinInputOutput="O"/>
    <Function Id="DV0_DATA9" FunctionName="DV0_DATA9" PinInputOutput="I"/>
    <Function Id="TxD3" FunctionName="TxD3" PinInputOutput="O"/>
  </Pin>
  <Pin Id="M4" PinNumber="M4">
    <Function Id="Vss" FunctionName="Vss" PinInputOutput="-"/>
  </Pin>
  <Pin Id="G15" PinNumber="G15">
    <Function Id="P3_10" FunctionName="P3_10" PinInputOutput="IO"/>
    <Function Id="A11" FunctionName="A11" PinInputOutput="O"/>
    <Function Id="SPBIO01_0" FunctionName="SPBIO01_0" PinInputOutput="IO"/>
    <Function Id="TIOC3B" FunctionName="TIOC3B" PinInputOutput="IO"/>
    <Function Id="DV0_DATA10" FunctionName="DV0_DATA10" PinInputOutput="I"/>
    <Function Id="RxD3" FunctionName="RxD3" PinInputOutput="I"/>
  </Pin>
  <Pin Id="G14" PinNumber="G14">
    <Function Id="P3_11" FunctionName="P3_11" PinInputOutput="IO"/>
    <Function Id="A12" FunctionName="A12" PinInputOutput="O"/>
    <Function Id="SPBIO11_0" FunctionName="SPBIO11_0" PinInputOutput="IO"/>
    <Function Id="TIOC3A" FunctionName="TIOC3A" PinInputOutput="IO"/>
    <Function Id="DV0_DATA11" FunctionName="DV0_DATA11" PinInputOutput="I"/>
  </Pin>
  <Pin Id="M12" PinNumber="M12">
    <Function Id="Vcc" FunctionName="Vcc" PinInputOutput="-"/>
  </Pin>
  <Pin Id="F15" PinNumber="F15">
    <Function Id="P3_12" FunctionName="P3_12" PinInputOutput="IO"/>
    <Function Id="A13" FunctionName="A13" PinInputOutput="O"/>
    <Function Id="SPBIO21_0" FunctionName="SPBIO21_0" PinInputOutput="IO"/>
    <Function Id="TIOC3C" FunctionName="TIOC3C" PinInputOutput="IO"/>
    <Function Id="DV0_DATA12" FunctionName="DV0_DATA12" PinInputOutput="I"/>
  </Pin>
  <Pin Id="M15" PinNumber="M15">
    <Function Id="Vss" FunctionName="Vss" PinInputOutput="-"/>
  </Pin>
  <Pin Id="F14" PinNumber="F14">
    <Function Id="P3_13" FunctionName="P3_13" PinInputOutput="IO"/>
    <Function Id="A14" FunctionName="A14" PinInputOutput="O"/>
    <Function Id="SPBIO31_0" FunctionName="SPBIO31_0" PinInputOutput="IO"/>
    <Function Id="TIOC3D" FunctionName="TIOC3D" PinInputOutput="IO"/>
    <Function Id="DV0_DATA13" FunctionName="DV0_DATA13" PinInputOutput="I"/>
  </Pin>
  <Pin Id="M11" PinNumber="M11">
    <Function Id="PVcc" FunctionName="PVcc" PinInputOutput="-"/>
  </Pin>
  <Pin Id="F13" PinNumber="F13">
    <Function Id="P3_14" FunctionName="P3_14" PinInputOutput="IO"/>
    <Function Id="A15" FunctionName="A15" PinInputOutput="O"/>
    <Function Id="VIO_CLK" FunctionName="VIO_CLK" PinInputOutput="I"/>
    <Function Id="SPDIF_IN" FunctionName="SPDIF_IN" PinInputOutput="I"/>
    <Function Id="DV0_DATA14" FunctionName="DV0_DATA14" PinInputOutput="I"/>
    <Function Id="SCK1" FunctionName="SCK1" PinInputOutput="IO"/>
    <Function Id="AUDIO_XOUT2" FunctionName="AUDIO_XOUT2" PinInputOutput="O"/>
  </Pin>
  <Pin Id="E14" PinNumber="E14">
    <Function Id="P1_0" FunctionName="P1_0" PinInputOutput="IO"/>
    <Function Id="RIIC0SCL" FunctionName="RIIC0SCL" PinInputOutput="IO"/>
    <Function Id="IRQ4" FunctionName="IRQ4" PinInputOutput="I"/>
    <Function Id="ET_RXD0" FunctionName="ET_RXD0" PinInputOutput="I"/>
    <Function Id="DV0_DATA0" FunctionName="DV0_DATA0" PinInputOutput="I"/>
  </Pin>
  <Pin Id="E15" PinNumber="E15">
    <Function Id="P1_1" FunctionName="P1_1" PinInputOutput="IO"/>
    <Function Id="RIIC0SDA" FunctionName="RIIC0SDA" PinInputOutput="IO"/>
    <Function Id="IRQ5" FunctionName="IRQ5" PinInputOutput="I"/>
    <Function Id="ET_RXD1" FunctionName="ET_RXD1" PinInputOutput="I"/>
    <Function Id="DV0_DATA1" FunctionName="DV0_DATA1" PinInputOutput="I"/>
  </Pin>
  <Pin Id="E13" PinNumber="E13">
    <Function Id="P1_2" FunctionName="P1_2" PinInputOutput="IO"/>
    <Function Id="RIIC1SCL" FunctionName="RIIC1SCL" PinInputOutput="IO"/>
    <Function Id="IRQ6" FunctionName="IRQ6" PinInputOutput="I"/>
    <Function Id="ET_RXD2" FunctionName="ET_RXD2" PinInputOutput="I"/>
    <Function Id="DV0_DATA2" FunctionName="DV0_DATA2" PinInputOutput="I"/>
  </Pin>
  <Pin Id="D15" PinNumber="D15">
    <Function Id="P1_3" FunctionName="P1_3" PinInputOutput="IO"/>
    <Function Id="RIIC1SDA" FunctionName="RIIC1SDA" PinInputOutput="IO"/>
    <Function Id="IRQ7" FunctionName="IRQ7" PinInputOutput="I"/>
    <Function Id="ET_RXD3" FunctionName="ET_RXD3" PinInputOutput="I"/>
    <Function Id="DV0_DATA3" FunctionName="DV0_DATA3" PinInputOutput="I"/>
  </Pin>
  <Pin Id="D14" PinNumber="D14">
    <Function Id="P1_4" FunctionName="P1_4" PinInputOutput="IO"/>
    <Function Id="RIIC2SCL" FunctionName="RIIC2SCL" PinInputOutput="IO"/>
    <Function Id="IRQ0" FunctionName="IRQ0" PinInputOutput="I"/>
    <Function Id="DREQ0" FunctionName="DREQ0" PinInputOutput="I"/>
    <Function Id="VIO_D0" FunctionName="VIO_D0" PinInputOutput="I"/>
  </Pin>
  <Pin Id="C15" PinNumber="C15">
    <Function Id="P1_5" FunctionName="P1_5" PinInputOutput="IO"/>
    <Function Id="RIIC2SDA" FunctionName="RIIC2SDA" PinInputOutput="IO"/>
    <Function Id="IRQ1" FunctionName="IRQ1" PinInputOutput="I"/>
    <Function Id="VIO_D1" FunctionName="VIO_D1" PinInputOutput="I"/>
  </Pin>
  <Pin Id="C14" PinNumber="C14">
    <Function Id="P1_6" FunctionName="P1_6" PinInputOutput="IO"/>
    <Function Id="RIIC3SCL" FunctionName="RIIC3SCL" PinInputOutput="IO"/>
    <Function Id="IRQ2" FunctionName="IRQ2" PinInputOutput="I"/>
    <Function Id="SSIRxD0" FunctionName="SSIRxD0" PinInputOutput="I"/>
    <Function Id="VIO_D2" FunctionName="VIO_D2" PinInputOutput="I"/>
  </Pin>
  <Pin Id="B15" PinNumber="B15">
    <Function Id="P1_7" FunctionName="P1_7" PinInputOutput="IO"/>
    <Function Id="RIIC3SDA" FunctionName="RIIC3SDA" PinInputOutput="IO"/>
    <Function Id="IRQ3" FunctionName="IRQ3" PinInputOutput="I"/>
    <Function Id="RxD2" FunctionName="RxD2" PinInputOutput="I"/>
    <Function Id="VIO_D3" FunctionName="VIO_D3" PinInputOutput="I"/>
  </Pin>
  <Pin Id="A14" PinNumber="A14">
    <Function Id="P3_15" FunctionName="P3_15" PinInputOutput="IO"/>
    <Function Id="A16" FunctionName="A16" PinInputOutput="O"/>
    <Function Id="VIO_FLD" FunctionName="VIO_FLD" PinInputOutput="I"/>
    <Function Id="DV0_DATA15" FunctionName="DV0_DATA15" PinInputOutput="I"/>
    <Function Id="TxD1" FunctionName="TxD1" PinInputOutput="O"/>
  </Pin>
  <Pin Id="B13" PinNumber="B13">
    <Function Id="P2_6" FunctionName="P2_6" PinInputOutput="IO"/>
    <Function Id="RD/WR#" FunctionName="RD/WR#" PinInputOutput="O"/>
    <Function Id="SSIRxD3" FunctionName="SSIRxD3" PinInputOutput="I"/>
    <Function Id="TIOC2A" FunctionName="TIOC2A" PinInputOutput="IO"/>
  </Pin>
  <Pin Id="C12" PinNumber="C12">
    <Function Id="P2_7" FunctionName="P2_7" PinInputOutput="IO"/>
    <Function Id="CS0#" FunctionName="CS0#" PinInputOutput="O"/>
    <Function Id="SSISCK3" FunctionName="SSISCK3" PinInputOutput="IO"/>
    <Function Id="TIOC1A" FunctionName="TIOC1A" PinInputOutput="IO"/>
    <Function Id="IRQ2" FunctionName="IRQ2" PinInputOutput="I"/>
  </Pin>
  <Pin Id="A13" PinNumber="A13">
    <Function Id="P2_8" FunctionName="P2_8" PinInputOutput="IO"/>
    <Function Id="RD#" FunctionName="RD#" PinInputOutput="O"/>
    <Function Id="SSITxD3" FunctionName="SSITxD3" PinInputOutput="O"/>
    <Function Id="TIOC0A" FunctionName="TIOC0A" PinInputOutput="IO"/>
    <Function Id="CAN0TX" FunctionName="CAN0TX" PinInputOutput="O"/>
  </Pin>
  <Pin Id="B12" PinNumber="B12">
    <Function Id="P2_9" FunctionName="P2_9" PinInputOutput="IO"/>
    <Function Id="A0" FunctionName="A0" PinInputOutput="O"/>
    <Function Id="SSIWS3" FunctionName="SSIWS3" PinInputOutput="IO"/>
    <Function Id="SCK0" FunctionName="SCK0" PinInputOutput="IO"/>
    <Function Id="IRQ1" FunctionName="IRQ1" PinInputOutput="I"/>
    <Function Id="CAN0RX" FunctionName="CAN0RX" PinInputOutput="I"/>
  </Pin>
  <Pin Id="N3" PinNumber="N3">
    <Function Id="Vss" FunctionName="Vss" PinInputOutput="-"/>
  </Pin>
  <Pin Id="A12" PinNumber="A12">
    <Function Id="USB_X1" FunctionName="USB_X1" PinInputOutput="I"/>
  </Pin>
  <Pin Id="B11" PinNumber="B11">
    <Function Id="USB_X2" FunctionName="USB_X2" PinInputOutput="O"/>
  </Pin>
  <Pin Id="B10" PinNumber="B10">
    <Function Id="DM1" FunctionName="DM1" PinInputOutput="IO"/>
  </Pin>
  <Pin Id="A10" PinNumber="A10">
    <Function Id="DP1" FunctionName="DP1" PinInputOutput="IO"/>
  </Pin>
  <Pin Id="C10" PinNumber="C10">
    <Function Id="VBUS1" FunctionName="VBUS1" PinInputOutput="I"/>
  </Pin>
  <Pin Id="A9" PinNumber="A9">
    <Function Id="DM0" FunctionName="DM0" PinInputOutput="IO"/>
  </Pin>
  <Pin Id="B9" PinNumber="B9">
    <Function Id="DP0" FunctionName="DP0" PinInputOutput="IO"/>
  </Pin>
  <Pin Id="C9" PinNumber="C9">
    <Function Id="VBUS0" FunctionName="VBUS0" PinInputOutput="I"/>
  </Pin>
  <Pin Id="B8" PinNumber="B8">
    <Function Id="REFRIN" FunctionName="REFRIN" PinInputOutput="I"/>
  </Pin>
  <Pin Id="D10" PinNumber="D10">
    <Function Id="USBAPVcc" FunctionName="USBAPVcc" PinInputOutput="-"/>
  </Pin>
  <Pin Id="C8" PinNumber="C8">
    <Function Id="USBAVcc" FunctionName="USBAVcc" PinInputOutput="-"/>
  </Pin>
  <Pin Id="N8" PinNumber="N8">
    <Function Id="Vss" FunctionName="Vss" PinInputOutput="-"/>
  </Pin>
  <Pin Id="P2" PinNumber="P2">
    <Function Id="Vss" FunctionName="Vss" PinInputOutput="-"/>
  </Pin>
  <Pin Id="C7" PinNumber="C7">
    <Function Id="P4_0" FunctionName="P4_0" PinInputOutput="IO"/>
    <Function Id="A17" FunctionName="A17" PinInputOutput="O"/>
    <Function Id="VIO_VD" FunctionName="VIO_VD" PinInputOutput="I"/>
    <Function Id="TIOC1B" FunctionName="TIOC1B" PinInputOutput="IO"/>
    <Function Id="ET_MDC" FunctionName="ET_MDC" PinInputOutput="O"/>
    <Function Id="CTS1#" FunctionName="CTS1#" PinInputOutput="IO"/>
  </Pin>
  <Pin Id="B7" PinNumber="B7">
    <Function Id="P4_1" FunctionName="P4_1" PinInputOutput="IO"/>
    <Function Id="A18" FunctionName="A18" PinInputOutput="O"/>
    <Function Id="VIO_HD" FunctionName="VIO_HD" PinInputOutput="I"/>
    <Function Id="TIOC2B" FunctionName="TIOC2B" PinInputOutput="IO"/>
    <Function Id="ET_MDIO" FunctionName="ET_MDIO" PinInputOutput="IO"/>
    <Function Id="RTS1#" FunctionName="RTS1#" PinInputOutput="IO"/>
  </Pin>
  <Pin Id="C6" PinNumber="C6">
    <Function Id="P4_2" FunctionName="P4_2" PinInputOutput="IO"/>
    <Function Id="A19" FunctionName="A19" PinInputOutput="O"/>
    <Function Id="SPBIO20_0" FunctionName="SPBIO20_0" PinInputOutput="IO"/>
    <Function Id="TRACEDATA2" FunctionName="TRACEDATA2" PinInputOutput="O"/>
  </Pin>
  <Pin Id="A6" PinNumber="A6">
    <Function Id="P4_3" FunctionName="P4_3" PinInputOutput="IO"/>
    <Function Id="A20" FunctionName="A20" PinInputOutput="O"/>
    <Function Id="SPBIO30_0" FunctionName="SPBIO30_0" PinInputOutput="IO"/>
    <Function Id="TRACEDATA3" FunctionName="TRACEDATA3" PinInputOutput="O"/>
  </Pin>
  <Pin Id="R1" PinNumber="R1">
    <Function Id="Vss" FunctionName="Vss" PinInputOutput="-"/>
  </Pin>
  <Pin Id="B6" PinNumber="B6">
    <Function Id="P4_4" FunctionName="P4_4" PinInputOutput="IO"/>
    <Function Id="A21" FunctionName="A21" PinInputOutput="O"/>
    <Function Id="SPBCLK_0" FunctionName="SPBCLK_0" PinInputOutput="O"/>
    <Function Id="TRACECLK" FunctionName="TRACECLK" PinInputOutput="O"/>
  </Pin>
  <Pin Id="A5" PinNumber="A5">
    <Function Id="P4_5" FunctionName="P4_5" PinInputOutput="IO"/>
    <Function Id="A22" FunctionName="A22" PinInputOutput="O"/>
    <Function Id="SPBSSL_0" FunctionName="SPBSSL_0" PinInputOutput="O"/>
    <Function Id="TRACECTL" FunctionName="TRACECTL" PinInputOutput="O"/>
  </Pin>
  <Pin Id="B5" PinNumber="B5">
    <Function Id="P4_6" FunctionName="P4_6" PinInputOutput="IO"/>
    <Function Id="A23" FunctionName="A23" PinInputOutput="O"/>
    <Function Id="SPBIO00_0" FunctionName="SPBIO00_0" PinInputOutput="IO"/>
    <Function Id="TRACEDATA0" FunctionName="TRACEDATA0" PinInputOutput="O"/>
  </Pin>
  <Pin Id="R3" PinNumber="R3">
    <Function Id="Vss" FunctionName="Vss" PinInputOutput="-"/>
  </Pin>
  <Pin Id="C5" PinNumber="C5">
    <Function Id="P4_7" FunctionName="P4_7" PinInputOutput="IO"/>
    <Function Id="A24" FunctionName="A24" PinInputOutput="O"/>
    <Function Id="SPBIO10_0" FunctionName="SPBIO10_0" PinInputOutput="IO"/>
    <Function Id="TRACEDATA1" FunctionName="TRACEDATA1" PinInputOutput="O"/>
  </Pin>
  <Pin Id="A4" PinNumber="A4">
    <Function Id="P5_0" FunctionName="P5_0" PinInputOutput="IO"/>
    <Function Id="D0" FunctionName="D0" PinInputOutput="IO"/>
    <Function Id="MMC_D4" FunctionName="MMC_D4" PinInputOutput="IO"/>
    <Function Id="ET_TXD0" FunctionName="ET_TXD0" PinInputOutput="O"/>
    <Function Id="DV0_DATA16" FunctionName="DV0_DATA16" PinInputOutput="I"/>
    <Function Id="LCD0_TCON0" FunctionName="LCD0_TCON0" PinInputOutput="O"/>
  </Pin>
  <Pin Id="P1" PinNumber="P1">
    <Function Id="PVcc" FunctionName="PVcc" PinInputOutput="-"/>
  </Pin>
  <Pin Id="B4" PinNumber="B4">
    <Function Id="P5_1" FunctionName="P5_1" PinInputOutput="IO"/>
    <Function Id="D1" FunctionName="D1" PinInputOutput="IO"/>
    <Function Id="MMC_D5" FunctionName="MMC_D5" PinInputOutput="IO"/>
    <Function Id="ET_TXD1" FunctionName="ET_TXD1" PinInputOutput="O"/>
    <Function Id="DV0_DATA17" FunctionName="DV0_DATA17" PinInputOutput="I"/>
    <Function Id="LCD0_TCON1" FunctionName="LCD0_TCON1" PinInputOutput="O"/>
  </Pin>
  <Pin Id="A3" PinNumber="A3">
    <Function Id="P5_2" FunctionName="P5_2" PinInputOutput="IO"/>
    <Function Id="D2" FunctionName="D2" PinInputOutput="IO"/>
    <Function Id="MMC_D6" FunctionName="MMC_D6" PinInputOutput="IO"/>
    <Function Id="ET_TXD2" FunctionName="ET_TXD2" PinInputOutput="O"/>
    <Function Id="DV0_DATA18" FunctionName="DV0_DATA18" PinInputOutput="I"/>
    <Function Id="LCD0_TCON2" FunctionName="LCD0_TCON2" PinInputOutput="O"/>
  </Pin>
  <Pin Id="N13" PinNumber="N13">
    <Function Id="Vcc" FunctionName="Vcc" PinInputOutput="-"/>
  </Pin>
  <Pin Id="P14" PinNumber="P14">
    <Function Id="Vcc" FunctionName="Vcc" PinInputOutput="-"/>
  </Pin>
  <Pin Id="R15" PinNumber="R15">
    <Function Id="Vcc" FunctionName="Vcc" PinInputOutput="-"/>
  </Pin>
  <Pin Id="D12" PinNumber="D12">
    <Function Id="Vss" FunctionName="Vss" PinInputOutput="-"/>
  </Pin>
  <Pin Id="H12" PinNumber="H12">
    <Function Id="Vss" FunctionName="Vss" PinInputOutput="-"/>
  </Pin>
</PinInformation>
